optimade_client/__init__.py
optimade_client/default_parameters.py
optimade_client/exceptions.py
optimade_client/informational.py
optimade_client/logger.py
optimade_client/query_filter.py
optimade_client/query_provider.py
optimade_client/summary.py
optimade_client/utils.py
optimade_client/warnings.py
optimade_client/cli/__init__.py
optimade_client/cli/run.py
optimade_client/cli/static/OPTIMADE-Client.ipynb
optimade_client/cli/static/voila.json
optimade_client/img/optimade-text-right-transparent-bg.png
optimade_client/subwidgets/__init__.py
optimade_client/subwidgets/filter_inputs.py
optimade_client/subwidgets/intrangeslider.py
optimade_client/subwidgets/multi_checkbox.py
optimade_client/subwidgets/output_summary.py
optimade_client/subwidgets/periodic_table.py
optimade_client/subwidgets/provider_database.py
optimade_client/subwidgets/results.py
optimade_client/subwidgets/sort_selector.py
optimade_client-2023.8.30.dist-info/LICENSE
optimade_client-2023.8.30.dist-info/METADATA
optimade_client-2023.8.30.dist-info/WHEEL
optimade_client-2023.8.30.dist-info/entry_points.txt
optimade_client-2023.8.30.dist-info/top_level.txt
optimade_client-2023.8.30.dist-info/RECORD
