Metadata-Version: 2.1
Name: optimade-client
Version: 2023.8.30
Summary: Voilà/Jupyter client for searching through OPTIMADE databases.
Home-page: https://github.com/CasperWA/voila-optimade-client
Author: Casper Welzel Andersen
Author-email: casper+github@welzel.nu
License: MIT License
Classifier: Development Status :: 5 - Production/Stable
Classifier: Framework :: AiiDA
Classifier: Framework :: Jupyter
Classifier: Intended Audience :: Science/Research
Classifier: License :: OSI Approved :: MIT License
Classifier: Operating System :: MacOS :: MacOS X
Classifier: Operating System :: POSIX :: Linux
Classifier: Operating System :: Microsoft :: Windows
Classifier: Programming Language :: Python :: 3 :: Only
Classifier: Programming Language :: Python :: 3.9
Classifier: Programming Language :: Python :: 3.10
Classifier: Programming Language :: Python :: 3.11
Classifier: Topic :: Database :: Front-Ends
Classifier: Topic :: Scientific/Engineering
Classifier: Topic :: Scientific/Engineering :: Chemistry
Classifier: Topic :: Scientific/Engineering :: Physics
Classifier: Topic :: Software Development :: Widget Sets
Requires-Python: >=3.9
License-File: LICENSE
Requires-Dist: appdirs ~=1.4.4
Requires-Dist: cachecontrol[filecache] ~=0.13.1
Requires-Dist: ipywidgets ~=7.7
Requires-Dist: ipywidgets-extended !=1.2.0,!=1.2.1,<2,>=1.1.1
Requires-Dist: nglview ~=3.0
Requires-Dist: optimade ~=0.25.1
Requires-Dist: pandas ~=2.0
Requires-Dist: requests ~=2.31
Requires-Dist: widget-periodictable ~=3.1
Provides-Extra: dev
Requires-Dist: pre-commit ~=3.3 ; extra == 'dev'
Requires-Dist: pylint ~=2.17 ; extra == 'dev'
Requires-Dist: codecov ~=2.1 ; extra == 'dev'
Requires-Dist: pytest ~=7.4 ; extra == 'dev'
Requires-Dist: pytest-cov ~=4.1 ; extra == 'dev'
Requires-Dist: pytest-tornasync ~=0.6.0.post2 ; extra == 'dev'
Requires-Dist: ase ~=3.22 ; extra == 'dev'
Requires-Dist: voila ~=0.5.1 ; extra == 'dev'
Provides-Extra: server
Requires-Dist: ase ~=3.22 ; extra == 'server'
Requires-Dist: voila ~=0.5.1 ; extra == 'server'
Provides-Extra: testing
Requires-Dist: codecov ~=2.1 ; extra == 'testing'
Requires-Dist: pytest ~=7.4 ; extra == 'testing'
Requires-Dist: pytest-cov ~=4.1 ; extra == 'testing'
Requires-Dist: pytest-tornasync ~=0.6.0.post2 ; extra == 'testing'
